MANIFEST.in
README.rst
requirements.txt
setup.py
bin/spinneret
spinneret/__init__.py
spinneret/commandline.py
spinneret/spider.py
spinneret/traffic.py
spinneret.egg-info/PKG-INFO
spinneret.egg-info/SOURCES.txt
spinneret.egg-info/dependency_links.txt
spinneret.egg-info/requires.txt
spinneret.egg-info/top_level.txt