Metadata-Version: 1.1
Name: spinneret
Version: 0.0.2
Summary: Quick web spider and traffic generator
Home-page: https://github.com/steder/spinneret
Author: Mike Steder
Author-email: steder@gmail.com
License: UNKNOWN
Platform: UNKNOWN
Classifier: Development Status :: 3 - Alpha
Classifier: Programming Language :: Python
Classifier: Programming Language :: Python :: 2
Classifier: Programming Language :: Python :: 2.7
Classifier: Topic :: Utilities
